geordnet/__init__.py
geordnet/__main__.py
geordnet-0.0.1.dist-info/LICENSE.txt
geordnet-0.0.1.dist-info/METADATA
geordnet-0.0.1.dist-info/WHEEL
geordnet-0.0.1.dist-info/top_level.txt
geordnet-0.0.1.dist-info/RECORD
