Metadata-Version: 2.1
Name: geordnet
Version: 0.0.1
Summary: geordnet
Author-email: Johannes <johannes-programming@mailfence.com>
License: The MIT License (MIT)
Project-URL: Documentation, https://pypi.org/project/geordnet
Project-URL: Download, https://pypi.org/project/geordnet/#files
Project-URL: Source, https://github.com/johannes-programming/geordnet
Classifier: License :: OSI Approved :: MIT License
Classifier: Programming Language :: Python
Classifier: Programming Language :: Python :: 3
Classifier: Programming Language :: Python :: 3 :: Only
Requires-Python: >=3.12.4
License-File: LICENSE.txt
